quilt_lang/__init__.py
quilt_lang-0.11.1.dist-info/METADATA
quilt_lang-0.11.1.dist-info/WHEEL
quilt_lang-0.11.1.dist-info/top_level.txt
quilt_lang-0.11.1.dist-info/RECORD
